acapy_revocation_demo/__init__.py
acapy_revocation_demo/__main__.py
acapy_revocation_demo/controller/__init__.py
acapy_revocation_demo/controller/api.py
acapy_revocation_demo/controller/connection.py
acapy_revocation_demo/controller/controller.py
acapy_revocation_demo/controller/credential_exchange.py
acapy_revocation_demo/controller/flows.py
acapy_revocation_demo/controller/invitation.py
acapy_revocation_demo/controller/onboarding.py
acapy_revocation_demo/controller/presentation_exchange.py
acapy_revocation_demo/controller/queue.py
acapy_revocation_demo/controller/record.py
acapy_revocation_demo/controller/utils.py
acapy_revocation_demo/scenarios.py
acapy_revocation_demo-0.1.5.dist-info/WHEEL
acapy_revocation_demo-0.1.5.dist-info/METADATA
acapy_revocation_demo-0.1.5.dist-info/RECORD
