Metadata-Version: 2.1
Name: acapy-revocation-demo
Version: 0.1.5
Summary: Demonstrate Indy AnonCreds revocation using ACA-Py
License: Apache-2.0
Author: Daniel Bluhm
Author-email: dbluhm@pm.me
Requires-Python: >=3.7,<4.0
Classifier: License :: OSI Approved :: Apache Software License
Classifier: Programming Language :: Python :: 3
Classifier: Programming Language :: Python :: 3.10
Classifier: Programming Language :: Python :: 3.7
Classifier: Programming Language :: Python :: 3.8
Classifier: Programming Language :: Python :: 3.9
Requires-Dist: acapy-client (==0.7.3.post0)
Requires-Dist: aiohttp (>=3.8.1,<4.0.0)
Requires-Dist: blessings (>=1.7,<2.0)
